{"User.d3cbf41d-e84d-44e6-8ffd-eadda5b07740": {"__class__": "User", "id": "d3cbf41d-e84d-44e6-8ffd-eadda5b07740", "created_at": "2024-03-23T23:28:03.634591", "updated_at": "2024-03-23T23:28:03.634593", "first_name": "Betty", "last_name": "Bar", "email": "airbnb@mail.com", "password": "root"}, "User.4a34ba3d-439f-40a1-8831-0766f6423a47": {"__class__": "User", "id": "4a34ba3d-439f-40a1-8831-0766f6423a47", "created_at": "2024-03-23T23:28:03.634770", "updated_at": "2024-03-23T23:28:03.634771", "first_name": "John", "email": "airbnb2@mail.com", "password": "root"}}